crudclient/README.md
crudclient/__init__.py
crudclient/__main__.py
crudclient/api.py
crudclient/auth.py
crudclient/client.py
crudclient/config.py
crudclient/crud/README.md
crudclient/crud/__init__.py
crudclient/crud/base.py
crudclient/crud/endpoint.py
crudclient/crud/operations.py
crudclient/crud/response_conversion.py
crudclient/exceptions.py
crudclient/groups.py
crudclient/http/README.md
crudclient/http/__init__.py
crudclient/http/client.py
crudclient/http/errors.py
crudclient/http/logging.py
crudclient/http/request.py
crudclient/http/response.py
crudclient/http/retry.py
crudclient/http/retry_conditions.py
crudclient/http/retry_strategies.py
crudclient/http/session.py
crudclient/http/utils.py
crudclient/models.py
crudclient/py.typed
crudclient/ratelimit/README.md
crudclient/ratelimit/__init__.py
crudclient/ratelimit/facade.py
crudclient/ratelimit/parsing/README.md
crudclient/ratelimit/parsing/__init__.py
crudclient/ratelimit/parsing/tripletex.py
crudclient/ratelimit/storage/__init__.py
crudclient/ratelimit/storage/file_json.py
crudclient/ratelimit/types.py
crudclient/response_strategies/README.md
crudclient/response_strategies/__init__.py
crudclient/response_strategies/base.py
crudclient/response_strategies/default.py
crudclient/response_strategies/path_based.py
crudclient/response_strategies/types.py
crudclient/testing/README.md
crudclient/testing/__init__.py
crudclient/testing/auth/README.md
crudclient/testing/auth/__init__.py
crudclient/testing/auth/api_key.py
crudclient/testing/auth/api_key_rate_limiter.py
crudclient/testing/auth/api_key_usage_tracker.py
crudclient/testing/auth/api_key_validator.py
crudclient/testing/auth/auth_error_verification.py
crudclient/testing/auth/auth_extraction_utils.py
crudclient/testing/auth/auth_header_verification.py
crudclient/testing/auth/auth_token_verification.py
crudclient/testing/auth/base.py
crudclient/testing/auth/basic.py
crudclient/testing/auth/bearer.py
crudclient/testing/auth/custom.py
crudclient-0.8.3.dist-info/COPYING
crudclient-0.8.3.dist-info/COPYING.LESSER
crudclient-0.8.3.dist-info/LICENSE
crudclient-0.8.3.dist-info/METADATA
crudclient-0.8.3.dist-info/WHEEL
crudclient-0.8.3.dist-info/RECORD
