Metadata-Version: 2.3
Name: crudclient
Version: 0.8.3
Summary: A flexible CRUD client for RESTful APIs
License: LGPL-3.0-or-later
Keywords: crud,api,client,rest
Author: leikaab
Author-email: nordavindltd@gmail.com
Requires-Python: >=3.11,<4.0
Classifier: License :: OSI Approved :: GNU Lesser General Public License v3 or later (LGPLv3+)
Classifier: Programming Language :: Python :: 3
Classifier: Programming Language :: Python :: 3.11
Classifier: Programming Language :: Python :: 3.12
Classifier: Programming Language :: Python :: 3.13
Classifier: Typing :: Typed
Provides-Extra: testing
Requires-Dist: apiconfig (>=0.3.2.dev0,<0.4.0)
Requires-Dist: appdirs (>=1.4,<2.0)
Requires-Dist: portalocker (>=2.8,<4.0)
Requires-Dist: pydantic[email] (>=2.8.2,<3.0.0)
Requires-Dist: requests (>=2.32.3,<3.0.0)
Project-URL: Bug Tracker, https://github.com/Leikaab/crudclient/issues
Project-URL: Documentation, https://github.com/Leikaab/crudclient#readme
Project-URL: Homepage, https://github.com/Leikaab/crudclient
Project-URL: Repository, https://github.com/Leikaab/crudclient
